topsy/__init__.py
topsy/__main__.py
topsy/cell_layout.py
topsy/colorbar.py
topsy/config.py
topsy/drawreason.py
topsy/line.py
topsy/loader.py
topsy/overlay.py
topsy/particle_buffers.py
topsy/performance.py
topsy/periodic_sph.py
topsy/progressive_render.py
topsy/scalebar.py
topsy/simcube.py
topsy/sph.py
topsy/split_buffers.py
topsy/text.py
topsy/util.py
topsy/view_synchronizer.py
topsy/visualizer.py
topsy/canvas/__init__.py
topsy/canvas/jupyter.py
topsy/canvas/offscreen.py
topsy/canvas/qt/__init__.py
topsy/canvas/qt/colormap.py
topsy/canvas/qt/lineedit.py
topsy/canvas/qt/recording.py
topsy/canvas/qt/icons/camera.png
topsy/canvas/qt/icons/linked.png
topsy/canvas/qt/icons/load_script.png
topsy/canvas/qt/icons/movie.png
topsy/canvas/qt/icons/record.png
topsy/canvas/qt/icons/rgb.png
topsy/canvas/qt/icons/save_script.png
topsy/canvas/qt/icons/stop.png
topsy/canvas/qt/icons/unlinked.png
topsy/colormap/__init__.py
topsy/colormap/implementation.py
topsy/colormap/surface.py
topsy/colormap/ui.py
topsy/recorder/__init__.py
topsy/recorder/interpolator.py
topsy/shaders/colormap.wgsl
topsy/shaders/line.wgsl
topsy/shaders/overlay.wgsl
topsy/shaders/smooth.wgsl
topsy/shaders/sph.wgsl
topsy/shaders/surface.wgsl
topsy-0.8.1.dist-info/entry_points.txt
topsy-0.8.1.dist-info/licenses/LICENSE
topsy-0.8.1.dist-info/WHEEL
topsy-0.8.1.dist-info/METADATA
topsy-0.8.1.dist-info/RECORD
