Metadata-Version: 2.4
Name: topsy
Version: 0.8.1
Summary: topsy - An astrophysics simulation visualization package based on webgpu, using pynbody for reading data
Author-email: Andrew Pontzen <a.pontzen@ucl.ac.uk>
Requires-Python: >=3.11
Classifier: Development Status :: 4 - Beta
Classifier: Intended Audience :: Science/Research
Classifier: License :: OSI Approved :: BSD License
Classifier: Operating System :: OS Independent
Classifier: Programming Language :: Python :: 3
Classifier: Topic :: Scientific/Engineering :: Visualization
License-File: LICENSE
Requires-Dist: numpy >=1.16.0
Requires-Dist: pynbody >=2.1.1
Requires-Dist: matplotlib >=3.6.0
Requires-Dist: pillow >=9.5.0
Requires-Dist: wgpu >= 0.22, <0.23
Requires-Dist: jupyter_rfb >=0.4.1
Requires-Dist: tqdm >=4.62.0
Requires-Dist: opencv-python >=4.8.0
Requires-Dist: PySide6 >= 6.5.0
Requires-Dist: superqt>=0.7.3
Requires-Dist: rendercanvas>=2.0.3
Requires-Dist: pytest >=6.2.0 ; extra == "test"
Requires-Dist: pytest-ipywidgets ; extra == "test"
Requires-Dist: tifffile ; extra == "test"
Project-URL: Home, https://github.com/pynbody/topsy
Provides-Extra: test
